boxmake/__init__.py
boxmake/cli/add.py
boxmake/cli/cli.py
boxmake/cli/create.py
boxmake/cli/list.py
boxmake/database/__init__.py
boxmake/database/create.py
boxmake/database/edit.py
boxmake-0.0.13.dist-info/METADATA
boxmake-0.0.13.dist-info/WHEEL
boxmake-0.0.13.dist-info/entry_points.txt
boxmake-0.0.13.dist-info/top_level.txt
boxmake-0.0.13.dist-info/RECORD
