Metadata-Version: 2.1
Name: boxmake
Version: 0.0.13
Summary: Build docker containers quickly with Spack integration.
Requires-Dist: docker
Requires-Dist: click
